ground_motion_tools/__init__.py
ground_motion_tools/enums/__init__.py
ground_motion_tools/enums/gm_data_enum.py
ground_motion_tools/enums/gm_im_enum.py
ground_motion_tools/enums/gm_spectrum_enum.py
ground_motion_tools/im.py
ground_motion_tools/io.py
ground_motion_tools/process.py
ground_motion_tools/sbs_integration_linear.py
ground_motion_tools/spectrum.py
ground_motion_tools-0.2.7.dist-info/METADATA
ground_motion_tools-0.2.7.dist-info/WHEEL
ground_motion_tools-0.2.7.dist-info/RECORD
